nonebot_plugin_MirlKoi/__init__.py
nonebot_plugin_MirlKoi-0.0.2.dist-info/LICENSE
nonebot_plugin_MirlKoi-0.0.2.dist-info/METADATA
nonebot_plugin_MirlKoi-0.0.2.dist-info/WHEEL
nonebot_plugin_MirlKoi-0.0.2.dist-info/top_level.txt
nonebot_plugin_MirlKoi-0.0.2.dist-info/RECORD
