Metadata-Version: 2.1
Name: nonebot-plugin-MirlKoi
Version: 0.0.2
Summary: 接入MirlKoi拿图的nonebot2壁纸插件
Home-page: https://github.com/KarisAya/nonebot_plugin_MirlKoi
Author: karisaya
Author-email: 1048827424@qq.com
License: MIT license
Platform: all
License-File: LICENSE
Requires-Dist: nonebot2
Requires-Dist: nonebot-adapter-onebot
